[{"Poll Date":"2015-05-07","Constituency":"Amber Valley","Constituency Code":"E14000533","Constituency URL":"http:\/\/statistics.data.gov.uk\/doc\/statistical-geography\/E14000533","Party":"UK Independence Party (UKIP)","Party ID":"PP85","Votes":"7263"},{"Poll Date":"2015-05-07","Constituency":"Amber Valley","Constituency Code":"E14000533","Constituency URL":"http:\/\/statistics.data.gov.uk\/doc\/statistical-geography\/E14000533","Party":"Green Party","Party ID":"PP63","Votes":"1087"},{"Poll Date":"2015-05-07","Constituency":"Amber Valley","Constituency Code":"E14000533","Constituency URL":"http:\/\/statistics.data.gov.uk\/doc\/statistical-geography\/E14000533","Party":"Labour Party","Party ID":"PP53","Votes":"15901"},{"Poll Date":"2015-05-07","Constituency":"Amber Valley","Constituency Code":"E14000533","Constituency URL":"http:\/\/statistics.data.gov.uk\/doc\/statistical-geography\/E14000533","Party":"Conservative Party","Party ID":"PP52","Votes":"20106"},{"Poll Date":"2015-05-07","Constituency":"Amber Valley","Constituency Code":"E14000533","Constituency URL":"http:\/\/statistics.data.gov.uk\/doc\/statistical-geography\/E14000533","Party":"Liberal Democrats","Party ID":"PP90","Votes":"1360"}]