[{"Poll Date":"2015-05-07","Constituency":"Cities of London and Westminster","Constituency Code":"E14000639","Constituency URL":"http:\/\/statistics.data.gov.uk\/doc\/statistical-geography\/E14000639","Party":"British National Party","Party ID":"PP106","Votes":"121967"},{"Poll Date":"2015-05-07","Constituency":"Cities of London and Westminster","Constituency Code":"E14000639","Constituency URL":"http:\/\/statistics.data.gov.uk\/doc\/statistical-geography\/E14000639","Party":"Christian Party","Party ID":"PP1992","Votes":"18784"},{"Poll Date":"2015-05-07","Constituency":"Cities of London and Westminster","Constituency Code":"E14000639","Constituency URL":"http:\/\/statistics.data.gov.uk\/doc\/statistical-geography\/E14000639","Party":"Conservative Party","Party ID":"PP52","Votes":"396847"},{"Poll Date":"2015-05-07","Constituency":"Cities of London and Westminster","Constituency Code":"E14000639","Constituency URL":"http:\/\/statistics.data.gov.uk\/doc\/statistical-geography\/E14000639","Party":"English Democrats Party","Party ID":"PP17","Votes":"32455"},{"Poll Date":"2015-05-07","Constituency":"Cities of London and Westminster","Constituency Code":"E14000639","Constituency URL":"http:\/\/statistics.data.gov.uk\/doc\/statistical-geography\/E14000639","Party":"Jury Team","Party ID":"PP999","Votes":"8721"},{"Poll Date":"2015-05-07","Constituency":"Cities of London and Westminster","Constituency Code":"E14000639","Constituency URL":"http:\/\/statistics.data.gov.uk\/doc\/statistical-geography\/E14000639","Party":"Liberal Democrats","Party ID":"PP90","Votes":"170246"},{"Poll Date":"2015-05-07","Constituency":"Cities of London and Westminster","Constituency Code":"E14000639","Constituency URL":"http:\/\/statistics.data.gov.uk\/doc\/statistical-geography\/E14000639","Party":"No2EU: Yes to Democracy","Party ID":"PP2164","Votes":"13415"},{"Poll Date":"2015-05-07","Constituency":"Cities of London and Westminster","Constituency Code":"E14000639","Constituency URL":"http:\/\/statistics.data.gov.uk\/doc\/statistical-geography\/E14000639","Party":"Pro Democracy: Libertas.eu","Party ID":"PP999","Votes":"6961"},{"Poll Date":"2015-05-07","Constituency":"Cities of London and Westminster","Constituency Code":"E14000639","Constituency URL":"http:\/\/statistics.data.gov.uk\/doc\/statistical-geography\/E14000639","Party":"Socialist Labour Party","Party ID":"PP73","Votes":"14724"},{"Poll Date":"2015-05-07","Constituency":"Cities of London and Westminster","Constituency Code":"E14000639","Constituency URL":"http:\/\/statistics.data.gov.uk\/doc\/statistical-geography\/E14000639","Party":"The Green Party","Party ID":"PP63","Votes":"88244"},{"Poll Date":"2015-05-07","Constituency":"Cities of London and Westminster","Constituency Code":"E14000639","Constituency URL":"http:\/\/statistics.data.gov.uk\/doc\/statistical-geography\/E14000639","Party":"The Labour Party","Party ID":"PP53","Votes":"240201"},{"Poll Date":"2015-05-07","Constituency":"Cities of London and Westminster","Constituency Code":"E14000639","Constituency URL":"http:\/\/statistics.data.gov.uk\/doc\/statistical-geography\/E14000639","Party":"United Kingdom Independence Party","Party ID":"PP85","Votes":"300471"}]