[{"Poll Date":"2015-05-07","Constituency":"Plymouth, Moor View","Constituency Code":"E14000879","Constituency URL":"http:\/\/statistics.data.gov.uk\/doc\/statistical-geography\/E14000879","Party":"Liberal Democrats","Party ID":"PP90","Votes":"1265"},{"Poll Date":"2015-05-07","Constituency":"Plymouth, Moor View","Constituency Code":"E14000879","Constituency URL":"http:\/\/statistics.data.gov.uk\/doc\/statistical-geography\/E14000879","Party":"Conservative Party","Party ID":"PP52","Votes":"16020"},{"Poll Date":"2015-05-07","Constituency":"Plymouth, Moor View","Constituency Code":"E14000879","Constituency URL":"http:\/\/statistics.data.gov.uk\/doc\/statistical-geography\/E14000879","Party":"UK Independence Party (UKIP)","Party ID":"PP85","Votes":"9152"},{"Poll Date":"2015-05-07","Constituency":"Plymouth, Moor View","Constituency Code":"E14000879","Constituency URL":"http:\/\/statistics.data.gov.uk\/doc\/statistical-geography\/E14000879","Party":"Green Party","Party ID":"PP63","Votes":"1023"},{"Poll Date":"2015-05-07","Constituency":"Plymouth, Moor View","Constituency Code":"E14000879","Constituency URL":"http:\/\/statistics.data.gov.uk\/doc\/statistical-geography\/E14000879","Party":"Trade Unionist and Socialist Coalition","Party ID":"PP804","Votes":"152"},{"Poll Date":"2015-05-07","Constituency":"Plymouth, Moor View","Constituency Code":"E14000879","Constituency URL":"http:\/\/statistics.data.gov.uk\/doc\/statistical-geography\/E14000879","Party":"Labour Party","Party ID":"PP53","Votes":"14994"}]