[{"Poll Date":"2015-05-07","Constituency":"Swansea West","Constituency Code":"W07000047","Constituency URL":"http:\/\/statistics.data.gov.uk\/doc\/statistical-geography\/W07000047","Party":"Labour and Co-operative Party","Party ID":"","Votes":"14967"},{"Poll Date":"2015-05-07","Constituency":"Swansea West","Constituency Code":"W07000047","Constituency URL":"http:\/\/statistics.data.gov.uk\/doc\/statistical-geography\/W07000047","Party":"UK Independence Party (UKIP)","Party ID":"PP85","Votes":"4744"},{"Poll Date":"2015-05-07","Constituency":"Swansea West","Constituency Code":"W07000047","Constituency URL":"http:\/\/statistics.data.gov.uk\/doc\/statistical-geography\/W07000047","Party":"Liberal Democrats","Party ID":"PP90","Votes":"3178"},{"Poll Date":"2015-05-07","Constituency":"Swansea West","Constituency Code":"W07000047","Constituency URL":"http:\/\/statistics.data.gov.uk\/doc\/statistical-geography\/W07000047","Party":"Trade Unionist and Socialist Coalition","Party ID":"PP804","Votes":"159"},{"Poll Date":"2015-05-07","Constituency":"Swansea West","Constituency Code":"W07000047","Constituency URL":"http:\/\/statistics.data.gov.uk\/doc\/statistical-geography\/W07000047","Party":"The Socialist Party of Great Britain","Party ID":"PP110","Votes":"49"},{"Poll Date":"2015-05-07","Constituency":"Swansea West","Constituency Code":"W07000047","Constituency URL":"http:\/\/statistics.data.gov.uk\/doc\/statistical-geography\/W07000047","Party":"Conservative Party","Party ID":"PP52","Votes":"7931"},{"Poll Date":"2015-05-07","Constituency":"Swansea West","Constituency Code":"W07000047","Constituency URL":"http:\/\/statistics.data.gov.uk\/doc\/statistical-geography\/W07000047","Party":"Plaid Cymru - The Party of Wales","Party ID":"PP77","Votes":"2266"},{"Poll Date":"2015-05-07","Constituency":"Swansea West","Constituency Code":"W07000047","Constituency URL":"http:\/\/statistics.data.gov.uk\/doc\/statistical-geography\/W07000047","Party":"Independent","Party ID":"","Votes":"78"},{"Poll Date":"2015-05-07","Constituency":"Swansea West","Constituency Code":"W07000047","Constituency URL":"http:\/\/statistics.data.gov.uk\/doc\/statistical-geography\/W07000047","Party":"Green Party","Party ID":"PP63","Votes":"1784"}]