[{"Poll Date":"2015-05-07","Constituency":"Tottenham","Constituency Code":"E14001002","Constituency URL":"http:\/\/statistics.data.gov.uk\/doc\/statistical-geography\/E14001002","Party":"Labour Party","Party ID":"PP53","Votes":"28654"},{"Poll Date":"2015-05-07","Constituency":"Tottenham","Constituency Code":"E14001002","Constituency URL":"http:\/\/statistics.data.gov.uk\/doc\/statistical-geography\/E14001002","Party":"The Peace Party \u2013 Non-violence, Justice, Environment","Party ID":"PP133","Votes":"291"},{"Poll Date":"2015-05-07","Constituency":"Tottenham","Constituency Code":"E14001002","Constituency URL":"http:\/\/statistics.data.gov.uk\/doc\/statistical-geography\/E14001002","Party":"Conservative Party","Party ID":"PP52","Votes":"5090"},{"Poll Date":"2015-05-07","Constituency":"Tottenham","Constituency Code":"E14001002","Constituency URL":"http:\/\/statistics.data.gov.uk\/doc\/statistical-geography\/E14001002","Party":"Liberal Democrats","Party ID":"PP90","Votes":"1756"},{"Poll Date":"2015-05-07","Constituency":"Tottenham","Constituency Code":"E14001002","Constituency URL":"http:\/\/statistics.data.gov.uk\/doc\/statistical-geography\/E14001002","Party":"UK Independence Party (UKIP)","Party ID":"PP85","Votes":"1512"},{"Poll Date":"2015-05-07","Constituency":"Tottenham","Constituency Code":"E14001002","Constituency URL":"http:\/\/statistics.data.gov.uk\/doc\/statistical-geography\/E14001002","Party":"Green Party","Party ID":"PP63","Votes":"3931"},{"Poll Date":"2015-05-07","Constituency":"Tottenham","Constituency Code":"E14001002","Constituency URL":"http:\/\/statistics.data.gov.uk\/doc\/statistical-geography\/E14001002","Party":"Trade Unionist and Socialist Coalition","Party ID":"PP804","Votes":"1324"}]