[{"Poll Date":"2015-05-07","Constituency":"West Suffolk","Constituency Code":"E14001034","Constituency URL":"http:\/\/statistics.data.gov.uk\/doc\/statistical-geography\/E14001034","Party":"UK Independence Party (UKIP)","Party ID":"PP85","Votes":"10700"},{"Poll Date":"2015-05-07","Constituency":"West Suffolk","Constituency Code":"E14001034","Constituency URL":"http:\/\/statistics.data.gov.uk\/doc\/statistical-geography\/E14001034","Party":"Conservative Party","Party ID":"PP52","Votes":"25684"},{"Poll Date":"2015-05-07","Constituency":"West Suffolk","Constituency Code":"E14001034","Constituency URL":"http:\/\/statistics.data.gov.uk\/doc\/statistical-geography\/E14001034","Party":"Labour Party","Party ID":"PP53","Votes":"8604"},{"Poll Date":"2015-05-07","Constituency":"West Suffolk","Constituency Code":"E14001034","Constituency URL":"http:\/\/statistics.data.gov.uk\/doc\/statistical-geography\/E14001034","Party":"Green Party","Party ID":"PP63","Votes":"1779"},{"Poll Date":"2015-05-07","Constituency":"West Suffolk","Constituency Code":"E14001034","Constituency URL":"http:\/\/statistics.data.gov.uk\/doc\/statistical-geography\/E14001034","Party":"Liberal Democrats","Party ID":"PP90","Votes":"2465"}]